areion-1.1.11.dist-info/METADATA
areion-1.1.11.dist-info/WHEEL
areion-1.1.11.dist-info/entry_points.txt
areion-1.1.11.dist-info/licenses/LICENSE
areion/__init__.py
areion/base/__init__.py
areion/base/base.py
areion/base/engine.py
areion/base/logger.py
areion/base/middleware.py
areion/base/orchestrator.py
areion/base/router.py
areion/core/__init__.py
areion/core/date_header_cache.py
areion/core/exceptions.py
areion/core/request.py
areion/core/response.py
areion/core/server.py
areion/default/__init__.py
areion/default/engine.py
areion/default/logger.py
areion/default/orchestrator.py
areion/default/router.py
areion/dev/__init__.py
areion/dev/swagger.py
areion/main.py
areion/tests/__init__.py
areion/tests/components/__init__.py
areion/tests/components/test_logger.py
areion/tests/components/test_orchestrator.py
areion/tests/components/test_router.py
areion/tests/core/__init__.py
areion/tests/core/test_date_header_cache.py
areion/tests/core/test_request.py
areion/tests/core/test_response.py
areion/tests/core/test_server.py
areion/tests/test_main.py
areion/utils/__init__.py
areion/utils/response_utils.py
areion-1.1.11.dist-info/RECORD
