Metadata-Version: 2.1
Name: areion
Version: 1.1.11
Summary: A lightweight, fast, and extensible asynchronous Python web server framework.
Keywords: python,api,framework,web,web-framework,http-server
Author-Email: Josh Caponigro <joshcaponigro@gmail.com>
License: Copyright (c) 2024 Joshua Caponigro
Classifier: Intended Audience :: Information Technology
Classifier: Intended Audience :: System Administrators
Classifier: Topic :: Internet
Classifier: Topic :: Software Development :: Libraries :: Application Frameworks
Classifier: Topic :: Software Development :: Libraries :: Python Modules
Classifier: Topic :: Software Development :: Libraries
Classifier: Topic :: Software Development
Classifier: Environment :: Web Environment
Classifier: Framework :: AsyncIO
Classifier: Programming Language :: Python :: 3.10
Classifier: Programming Language :: Python :: 3.11
Classifier: Programming Language :: Python :: 3.12
Classifier: Topic :: Internet :: WWW/HTTP :: HTTP Servers
Classifier: Topic :: Internet :: WWW/HTTP
Classifier: Development Status :: 4 - Beta
Classifier: License :: OSI Approved :: MIT License
Classifier: Operating System :: OS Independent
Project-URL: Homepage, https://github.com/JoshCap20/areion
Project-URL: Repository, https://github.com/JoshCap20/areion
Project-URL: Documentation, https://github.com/JoshCap20/areion/blob/main/README.md
Project-URL: Issues, https://github.com/JoshCap20/areion/issues
Requires-Python: >=3.10
Requires-Dist: jinja2>=3.0.0
Requires-Dist: apscheduler>=3.0.0
Requires-Dist: orjson>=3.0.0
Requires-Dist: uvloop>=0.20.0
Requires-Dist: httptools>=0.6.1
